{
  "editor:follow-link": [],
  "file-explorer:reveal-active-file": [
    {
      "modifiers": [
        "Mod",
        "Shift"
      ],
      "key": "E"
    }
  ],
  "cycle-through-panes:focus-on-last-active-pane-reverse": [
    {
      "modifiers": [
        "Mod"
      ],
      "key": "Tab"
    }
  ],
  "cycle-through-panes:focus-on-last-active-pane": [
    {
      "modifiers": [
        "Mod",
        "Shift"
      ],
      "key": "Tab"
    }
  ],
  "workspace:next-tab": [
    {
      "modifiers": [
        "Mod"
      ],
      "key": "Tab"
    }
  ],
  "workspace:previous-tab": [
    {
      "modifiers": [
        "Mod",
        "Shift"
      ],
      "key": "Tab"
    }
  ],
  "editor:toggle-numbered-list": [
    {
      "modifiers": [
        "Mod",
        "Shift"
      ],
      "key": "1"
    }
  ],
  "editor:toggle-bullet-list": [
    {
      "modifiers": [
        "Mod",
        "Shift"
      ],
      "key": "-"
    }
  ],
  "workspace:close-window": [],
  "workspace:close-tab-group": [
    {
      "modifiers": [
        "Mod",
        "Shift"
      ],
      "key": "W"
    }
  ],
  "command-palette:open": [
    {
      "modifiers": [
        "Mod",
        "Shift"
      ],
      "key": "P"
    }
  ],
  "app:toggle-left-sidebar": [
    {
      "modifiers": [
        "Mod",
        "Shift"
      ],
      "key": "B"
    }
  ],
  "editor:toggle-strikethrough": [
    {
      "modifiers": [
        "Mod",
        "Shift"
      ],
      "key": "S"
    }
  ],
  "open-with-default-app:show": [
    {
      "modifiers": [
        "Mod",
        "Shift"
      ],
      "key": "Enter"
    }
  ],
  "app:toggle-right-sidebar": [
    {
      "modifiers": [
        "Alt",
        "Mod",
        "Shift"
      ],
      "key": "B"
    }
  ],
  "app:open-settings": [
    {
      "modifiers": [
        "Mod"
      ],
      "key": "."
    }
  ],
  "markdown:add-metadata-property": [],
  "workspace:close-others": [
    {
      "modifiers": [
        "Alt",
        "Mod"
      ],
      "key": "W"
    }
  ],
  "file-explorer:new-file": [],
  "file-explorer:new-file-in-new-pane": [],
  "editor:delete-paragraph": [],
  "workspace:goto-last-tab": []
}